Workbook

Sheet Informe Diario
A1: GRIDO - INFORME DIARIO DE VENTAS | 27/09/2026 | T1: A desarrollar a futuro
A2: Generado: 27/09/2026 | Escalada - Fiorito - Lanus
A3: METRICAS CLAVE
D4: VENTAS TOTALES | G4: TRANSACCIONES | J4: TICKET PROMEDIO | M4: SOCIOS CLUB GRIDO
D5: =G26 | G5: =I26 | J5: =H26 | M5: =O26
A8: ALERTA = %SV por debajo del estandar (15%) | I8: SOBREVENTAS | O8: CLUB GRIDO | T8: CLIMA EN EL TURNO
A9: Sucursal / Cajero | B9: Turno | C9: Caja | D9: Horario | E9: Horas | F9: Kilos | G9: Ventas ($) | H9: Ticket Prom. ($) | I9: Tickets | J9: SV Activadas | K9: SV Aceptadas | L9: %SV | M9: Promos ($) | N9: %Promos | O9: Nuevos Socios | P9: Kilos Club Grido | Q9: %Kilos CG /Kilos | R9: Anuladas | S9: Dif. de Caja | T9: Sensación térmica promedio (°C) | U9: Lluvia (mm) | V9: Condición climática
A10: Fiorito | B10: Todos | E10: =SUM(E11:E14) | F10: =SUM(F11:F14) | G10: =SUM(G11:G14) | H10: =IFERROR(G10/I10,"") | I10: =SUM(I11:I14) | J10: =SUM(J11:J14) | K10: =SUM(K11:K14) | L10: =IFERROR(K10/J10,"") | M10: =SUM(M11:M14) | N10: =IFERROR(M10/G10,"") | O10: =SUM(O11:O14) | P10: =SUM(P11:P14) | Q10: =IFERROR(P10/F10,"") | R10: =SUM(R11:R14) | S10: =SUM(S11:S14) | T10: 14.4 | U10: 7.1 | V10: Llovizna leve
A11: Candela | B11: 9823 | C11: 2 | D11: 10:12 a 17:06 | E11: 6.9 | F11: 49.7 | G11: 869960 | H11: =IFERROR(G11/I11,"") | I11: 59 | J11: 55 | K11: 12 | L11: =IFERROR(K11/J11,"") | M11: 0 | N11: =IFERROR(M11/G11,"") | O11: 2 | P11: 27.5 | Q11: =IFERROR(P11/F11,"") | R11: 3 | S11: 1000 | T11: 14 | U11: 6.6 | V11: Llovizna leve
A12: Ailen | B12: 9825 | C12: 2 | D12: 17:20 a 22:46 | E12: 5.4 | F12: 58.2 | G12: 1033900 | H12: =IFERROR(G12/I12,"") | I12: 75 | J12: 71 | K12: 6 | L12: =IFERROR(K12/J12,"") | M12: 14000 | N12: =IFERROR(M12/G12,"") | O12: 3 | P12: 29 | Q12: =IFERROR(P12/F12,"") | R12: 1 | S12: 0 | T12: 15 | U12: 0.6 | V12: Mayormente despejado
A13: Veronica | B13: 11774 | C13: 1 | D13: 14:12 a 17:11 | E13: 3 | F13: 17.9 | G13: 304237 | H13: =IFERROR(G13/I13,"") | I13: 19 | J13: 13 | K13: 2 | L13: =IFERROR(K13/J13,"") | M13: 0 | N13: =IFERROR(M13/G13,"") | O13: 0 | P13: 9.5 | Q13: =IFERROR(P13/F13,"") | R13: 0 | S13: 31 | T13: 14.4 | U13: 4.1 | V13: Llovizna leve
A14: Luana | B14: 11776 | C14: 1 | D14: 17:23 a 21:35 | E14: 4.2 | F14: 39.4 | G14: 629046 | H14: =IFERROR(G14/I14,"") | I14: 36 | J14: 23 | K14: 3 | L14: =IFERROR(K14/J14,"") | M14: 54800 | N14: =IFERROR(M14/G14,"") | O14: 0 | P14: 13.6 | Q14: =IFERROR(P14/F14,"") | R14: 0 | S14: 992 | T14: 15.1 | U14: 0.1 | V14: Mayormente despejado
A15: Escalada | B15: Todos | E15: =SUM(E16:E20) | F15: =SUM(F16:F20) | G15: =SUM(G16:G20) | H15: =IFERROR(G15/I15,"") | I15: =SUM(I16:I20) | J15: =SUM(J16:J20) | K15: =SUM(K16:K20) | L15: =IFERROR(K15/J15,"") | M15: =SUM(M16:M20) | N15: =IFERROR(M15/G15,"") | O15: =SUM(O16:O20) | P15: =SUM(P16:P20) | Q15: =IFERROR(P15/F15,"") | R15: =SUM(R16:R20) | S15: =SUM(S16:S20) | T15: 14.2 | U15: 7.4 | V15: Llovizna leve
A16: Eliseo | B16: 8470 | C16: 2 | D16: 10:18 a 15:00 | E16: 4.7 | F16: 22 | G16: 375557.01 | H16: =IFERROR(G16/I16,"") | I16: 25 | J16: 19 | K16: 2 | L16: =IFERROR(K16/J16,"") | M16: 64560 | N16: =IFERROR(M16/G16,"") | O16: 0 | P16: 3.6 | Q16: =IFERROR(P16/F16,"") | R16: 2 | S16: 0 | T16: 13.7 | U16: 3.4 | V16: Llovizna moderada
A17: Silvia | B17: 8471 | C17: 2 | D17: 15:07 a 19:02 | E17: 3.9 | F17: 33 | G17: 618817.01 | H17: =IFERROR(G17/I17,"") | I17: 50 | J17: 30 | K17: 9 | L17: =IFERROR(K17/J17,"") | M17: 0 | N17: =IFERROR(M17/G17,"") | O17: 3 | P17: 13.5 | Q17: =IFERROR(P17/F17,"") | R17: 0 | S17: 0 | T17: 14.7 | U17: 3.2 | V17: Llovizna leve
A18: Emiliano | B18: 8472 | C18: 2 | D18: 19:18 a 22:29 | E18: 3.2 | F18: 34.8 | G18: 603212 | H18: =IFERROR(G18/I18,"") | I18: 47 | J18: 21 | K18: 0 | L18: =IFERROR(K18/J18,"") | M18: 33700 | N18: =IFERROR(M18/G18,"") | O18: 4 | P18: 9.2 | Q18: =IFERROR(P18/F18,"") | R18: 1 | S18: 0 | T18: 15 | U18: 0.5 | V18: Mayormente despejado
A19: Camila | B19: 9993 | C19: 1 | D19: 12:56 a 13:28 | E19: 0.5 | F19: 2.5 | G19: 51100 | H19: =IFERROR(G19/I19,"") | I19: 4 | J19: 4 | K19: 0 | L19: =IFERROR(K19/J19,"") | M19: 0 | N19: =IFERROR(M19/G19,"") | O19: 0 | P19: 2.5 | Q19: =IFERROR(P19/F19,"") | R19: 0 | S19: 0 | T19: 14.4 | U19: 1.9 | V19: Chaparrones leves
A20: Facundo | B20: 9994 | C20: 1 | D20: 21:13 a 01:00 | E20: 3.8 | F20: 6.4 | G20: 127100 | H20: =IFERROR(G20/I20,"") | I20: 12 | J20: 11 | K20: 3 | L20: =IFERROR(K20/J20,"") | M20: 0 | N20: =IFERROR(M20/G20,"") | O20: 1 | P20: 5.9 | Q20: =IFERROR(P20/F20,"") | R20: 0 | S20: 0 | T20: 14.1 | U20: 0.8 | V20: Llovizna leve
A21: Lanus Oeste | B21: Todos | E21: =SUM(E22:E25) | F21: =SUM(F22:F25) | G21: =SUM(G22:G25) | H21: =IFERROR(G21/I21,"") | I21: =SUM(I22:I25) | J21: =SUM(J22:J25) | K21: =SUM(K22:K25) | L21: =IFERROR(K21/J21,"") | M21: =SUM(M22:M25) | N21: =IFERROR(M21/G21,"") | O21: =SUM(O22:O25) | P21: =SUM(P22:P25) | Q21: =IFERROR(P21/F21,"") | R21: =SUM(R22:R25) | S21: =SUM(S22:S25) | T21: 14.2 | U21: 7.4 | V21: Llovizna leve
A22: Oscar | B22: 13390 | C22: 1 | D22: 11:37 a 16:53 | E22: 5.3 | F22: 50.5 | G22: 923930 | H22: =IFERROR(G22/I22,"") | I22: 60 | J22: 53 | K22: 7 | L22: =IFERROR(K22/J22,"") | M22: 42100 | N22: =IFERROR(M22/G22,"") | O22: 1 | P22: 28.3 | Q22: =IFERROR(P22/F22,"") | R22: 3 | S22: 0 | T22: 14.1 | U22: 6.2 | V22: Chaparrones leves
A23: Wanda | B23: 13391 | C23: 1 | D23: 17:12 a 00:38 | E23: 7.4 | F23: 63.3 | G23: 1071920 | H23: =IFERROR(G23/I23,"") | I23: 81 | J23: 76 | K23: 6 | L23: =IFERROR(K23/J23,"") | M23: 59760 | N23: =IFERROR(M23/G23,"") | O23: 1 | P23: 22.5 | Q23: =IFERROR(P23/F23,"") | R23: 4 | S23: 2550 | T23: 14.6 | U23: 1 | V23: Llovizna leve
A24: Fiorella | B24: 13889 | C24: 2 | D24: 10:10 a 16:53 | E24: 6.7 | F24: 17.5 | G24: 285220 | H24: =IFERROR(G24/I24,"") | I24: 17 | J24: 12 | K24: 0 | L24: =IFERROR(K24/J24,"") | M24: 39120.02 | N24: =IFERROR(M24/G24,"") | O24: 0 | P24: 5.7 | Q24: =IFERROR(P24/F24,"") | R24: 1 | S24: 59600 | T24: 13.9 | U24: 6.5 | V24: Llovizna leve
A25: Agustin | B25: 13891 | C25: 2 | D25: 17:48 a 23:10 | E25: 5.4 | F25: 16.6 | G25: 238760 | H25: =IFERROR(G25/I25,"") | I25: 11 | J25: 5 | K25: 0 | L25: =IFERROR(K25/J25,"") | M25: 63350.01 | N25: =IFERROR(M25/G25,"") | O25: 0 | P25: 8.5 | Q25: =IFERROR(P25/F25,"") | R25: 0 | S25: 0 | T25: 14.8 | U25: 0.8 | V25: Mayormente despejado
A26: TOTAL | E26: =E10+E15+E21 | F26: =F10+F15+F21 | G26: =G10+G15+G21 | H26: =IFERROR(G26/I26,"") | I26: =I10+I15+I21 | J26: =J10+J15+J21 | K26: =K10+K15+K21 | L26: =IFERROR(K26/J26,"") | M26: =M10+M15+M21 | N26: =IFERROR(M26/G26,"") | O26: =O10+O15+O21 | P26: =P10+P15+P21 | Q26: =IFERROR(P26/F26,"") | R26: =R10+R15+R21 | S26: =S10+S15+S21 | T26: 14.2 | U26: 7.4 | V26: Llovizna leve

Sheet Productos
A1: PRODUCTOS VENDIDOS · 27/09/2026
A2: Todas las unidades vendidas por sucursal, incluidas las que salieron dentro de promociones y sobreventas. Fuente: DF_DTW.
A4: Sucursal | B4: Rubro | C4: Producto | D4: Cantidad | E4: Kilos | F4: Venta | H4: TOP 10 PRODUCTOS POR CANTIDAD · LAS 3 SUCURSALES JUNTAS
A5: Fiorito | B5: (sin rubro) | C5: DESCUENTO PEDIGRIDO | D5: 1 | E5: 0 | F5: -6400 | H5: Producto | I5: Fiorito | J5: Escalada | K5: Lanus Oeste | L5: Total | M5: % de las unidades
A6: Fiorito | B6: CAFETERIA | C6: CHOCOLATADA GRANDE | D6: 2 | E6: 0 | F6: 2400 | H6: 1 KILO | I6: =SUMIFS($D$5:$D$211,$A$5:$A$211,"Fiorito",$C$5:$C$211,H6) -> 43 | J6: =SUMIFS($D$5:$D$211,$A$5:$A$211,"Escalada",$C$5:$C$211,H6) -> 23 | K6: =SUMIFS($D$5:$D$211,$A$5:$A$211,"Lanus Oeste",$C$5:$C$211,H6) -> 41 | L6: =SUM(I6:K6) -> 107 | M6: =IF(SUM($D$5:$D$211)=0,0,L6/SUM($D$5:$D$211)) -> 0.11076605
A7: Fiorito | B7: CAFETERIA | C7: CAFE CAPUCCINO | D7: 2 | E7: 0 | F7: 6600 | H7: 1/4 KILO | I7: =SUMIFS($D$5:$D$211,$A$5:$A$211,"Fiorito",$C$5:$C$211,H7) -> 40 | J7: =SUMIFS($D$5:$D$211,$A$5:$A$211,"Escalada",$C$5:$C$211,H7) -> 12 | K7: =SUMIFS($D$5:$D$211,$A$5:$A$211,"Lanus Oeste",$C$5:$C$211,H7) -> 33 | L7: =SUM(I7:K7) -> 85 | M7: =IF(SUM($D$5:$D$211)=0,0,L7/SUM($D$5:$D$211)) -> 0.087991718
A8: Fiorito | B8: CAFETERIA | C8: MEDIALUNA EXTRA DULCE PRECOCIDA | D8: 1 | E8: 0 | F8: 1000 | H8: 1/2 KILO | I8: =SUMIFS($D$5:$D$211,$A$5:$A$211,"Fiorito",$C$5:$C$211,H8) -> 34 | J8: =SUMIFS($D$5:$D$211,$A$5:$A$211,"Escalada",$C$5:$C$211,H8) -> 17 | K8: =SUMIFS($D$5:$D$211,$A$5:$A$211,"Lanus Oeste",$C$5:$C$211,H8) -> 21 | L8: =SUM(I8:K8) -> 72 | M8: =IF(SUM($D$5:$D$211)=0,0,L8/SUM($D$5:$D$211)) -> 0.074534161
A9: Fiorito | B9: CAFETERIA | C9: CAFÉ ESPRESSO DOBLE GRANDE | D9: 1 | E9: 0 | F9: 3300 | H9: FRAMBUESAS DOBLE CHOCOLATE - GRIDO | I9: =SUMIFS($D$5:$D$211,$A$5:$A$211,"Fiorito",$C$5:$C$211,H9) -> 7 | J9: =SUMIFS($D$5:$D$211,$A$5:$A$211,"Escalada",$C$5:$C$211,H9) -> 11 | K9: =SUMIFS($D$5:$D$211,$A$5:$A$211,"Lanus Oeste",$C$5:$C$211,H9) -> 15 | L9: =SUM(I9:K9) -> 33 | M9: =IF(SUM($D$5:$D$211)=0,0,L9/SUM($D$5:$D$211)) -> 0.034161491
A10: Fiorito | B10: CONGELADOS | C10: FRAMBUESAS DOBLE CHOCOLATE - GRIDO | D10: 7 | E10: 0.84 | F10: 39200 | H10: GIGANTE 2 BOCHAS | I10: =SUMIFS($D$5:$D$211,$A$5:$A$211,"Fiorito",$C$5:$C$211,H10) -> 9 | J10: =SUMIFS($D$5:$D$211,$A$5:$A$211,"Escalada",$C$5:$C$211,H10) -> 14 | K10: =SUMIFS($D$5:$D$211,$A$5:$A$211,"Lanus Oeste",$C$5:$C$211,H10) -> 10 | L10: =SUM(I10:K10) -> 33 | M10: =IF(SUM($D$5:$D$211)=0,0,L10/SUM($D$5:$D$211)) -> 0.034161491
A11: Fiorito | B11: CONGELADOS | C11: FRUTILLAS DOBLE CHOCOLATE - GRIDO | D11: 5 | E11: 0.6 | F11: 28000 | H11: PALITO BOMBÓN X10 UN. | I11: =SUMIFS($D$5:$D$211,$A$5:$A$211,"Fiorito",$C$5:$C$211,H11) -> 9 | J11: =SUMIFS($D$5:$D$211,$A$5:$A$211,"Escalada",$C$5:$C$211,H11) -> 7 | K11: =SUMIFS($D$5:$D$211,$A$5:$A$211,"Lanus Oeste",$C$5:$C$211,H11) -> 13 | L11: =SUM(I11:K11) -> 29 | M11: =IF(SUM($D$5:$D$211)=0,0,L11/SUM($D$5:$D$211)) -> 0.030020704
A12: Fiorito | B12: CUCURUCH. | C12: CUPS BLACK X 3 | D12: 8 | E12: 0 | F12: 9600 | H12: BOMBON ESCOCES EN CAJA X 8 | I12: =SUMIFS($D$5:$D$211,$A$5:$A$211,"Fiorito",$C$5:$C$211,H12) -> 4 | J12: =SUMIFS($D$5:$D$211,$A$5:$A$211,"Escalada",$C$5:$C$211,H12) -> 10 | K12: =SUMIFS($D$5:$D$211,$A$5:$A$211,"Lanus Oeste",$C$5:$C$211,H12) -> 9 | L12: =SUM(I12:K12) -> 23 | M12: =IF(SUM($D$5:$D$211)=0,0,L12/SUM($D$5:$D$211)) -> 0.023809524
A13: Fiorito | B13: CUCURUCH. | C13: CUPS CONITO X 5 UN. | D13: 4 | E13: 0 | F13: 4000 | H13: BOMBON ESCOCES X UNIDAD | I13: =SUMIFS($D$5:$D$211,$A$5:$A$211,"Fiorito",$C$5:$C$211,H13) -> 5 | J13: =SUMIFS($D$5:$D$211,$A$5:$A$211,"Escalada",$C$5:$C$211,H13) -> 5 | K13: =SUMIFS($D$5:$D$211,$A$5:$A$211,"Lanus Oeste",$C$5:$C$211,H13) -> 12 | L13: =SUM(I13:K13) -> 22 | M13: =IF(SUM($D$5:$D$211)=0,0,L13/SUM($D$5:$D$211)) -> 0.022774327
A14: Fiorito | B14: CUCURUCH. | C14: CUPS CLÁSICO BOCA ANCHA X3 | D14: 1 | E14: 0 | F14: 1200 | H14: PALITO FRUTAL FRUTILLA X UNIDAD | I14: =SUMIFS($D$5:$D$211,$A$5:$A$211,"Fiorito",$C$5:$C$211,H14) -> 9 | J14: =SUMIFS($D$5:$D$211,$A$5:$A$211,"Escalada",$C$5:$C$211,H14) -> 7 | K14: =SUMIFS($D$5:$D$211,$A$5:$A$211,"Lanus Oeste",$C$5:$C$211,H14) -> 5 | L14: =SUM(I14:K14) -> 21 | M14: =IF(SUM($D$5:$D$211)=0,0,L14/SUM($D$5:$D$211)) -> 0.02173913
A15: Fiorito | B15: DELIVERY | C15: ENVIO A DOMICILIO | D15: 41 | E15: 0 | F15: 61323 | H15: BOMBON FRUTEZZA XU. | I15: =SUMIFS($D$5:$D$211,$A$5:$A$211,"Fiorito",$C$5:$C$211,H15) -> 6 | J15: =SUMIFS($D$5:$D$211,$A$5:$A$211,"Escalada",$C$5:$C$211,H15) -> 8 | K15: =SUMIFS($D$5:$D$211,$A$5:$A$211,"Lanus Oeste",$C$5:$C$211,H15) -> 4 | L15: =SUM(I15:K15) -> 18 | M15: =IF(SUM($D$5:$D$211)=0,0,L15/SUM($D$5:$D$211)) -> 0.01863354
A16: Fiorito | B16: FAMILIAR | C16: FAMNº1 (CHOCOLATE/D.LECHE/AMERICANA) | D16: 6 | E16: 9.6 | F16: 105600
A17: Fiorito | B17: FAMILIAR | C17: FAMNº4 (D.LECHE G/VAINILLA/CHOCOLATE) | D17: 4 | E17: 6.4 | F17: 70400
A18: Fiorito | B18: FAMILIAR | C18: FAMNº3 (VAINILLA/FRUTILLA/GRANIZADO) | D18: 4 | E18: 6.4 | F18: 70400
A19: Fiorito | B19: FAMILIAR | C19: FAMNº2 (AMERICANA/FRUTILLA/DDL GRANIZADO) | D19: 3 | E19: 4.8 | F19: 52800
A20: Fiorito | B20: FRIZZIO | C20: PIZZA CEBOLLA | D20: 2 | E20: 1.08 | F20: 14800
A21: Fiorito | B21: GRIDO TOPS | C21: GRIDO TOPS SALSA FRUTILLA | D21: 1 | E21: 0 | F21: 500
A22: Fiorito | B22: GRIDO TOPS | C22: GRIDO TOPS - SALSA DULCE DE LECHE | D22: 1 | E22: 0 | F22: 500
A23: Fiorito | B23: GRIDO TOPS | C23: GRIDO TOPS - SALSA CHOCOLATE | D23: 1 | E23: 0 | F23: 500
A24: Fiorito | B24: GRIDOS | C24: CAPUCCINO GRIDO | D24: 9 | E24: 1.44 | F24: 39600
A25: Fiorito | B25: GRIDOS | C25: VELA NUMERO X UN | D25: 6 | E25: 0 | F25: 7200
A26: Fiorito | B26: GRIDOS | C26: GRIDO BATIDO | D26: 5 | E26: 0.8 | F26: 21500 | H26: TOP 10 PRODUCTOS POR CANTIDAD · FIORITO
A27: Fiorito | B27: HELADO X KILO | C27: 1 KILO | D27: 43 | E27: 43 | F27: 729300 | H27: Producto | I27: Cantidad | J27: Venta | K27: % de las unidades
A28: Fiorito | B28: HELADO X KILO | C28: 1/4 KILO | D28: 40 | E28: 10 | F28: 248800 | H28: 1 KILO | I28: =SUMIFS($D$5:$D$211,$A$5:$A$211,"Fiorito",$C$5:$C$211,H28) -> 43 | J28: =SUMIFS($F$5:$F$211,$A$5:$A$211,"Fiorito",$C$5:$C$211,H28) -> 729300 | K28: =IF(SUMIF($A$5:$A$211,"Fiorito",$D$5:$D$211)=0,0,I28/SUMIF($A$5:$A$211,"Fiorito",$D$5:$D$211)) -> 0.11025641
A29: Fiorito | B29: HELADO X KILO | C29: 1/2 KILO | D29: 34 | E29: 17 | F29: 324200 | H29: 1/4 KILO | I29: =SUMIFS($D$5:$D$211,$A$5:$A$211,"Fiorito",$C$5:$C$211,H29) -> 40 | J29: =SUMIFS($F$5:$F$211,$A$5:$A$211,"Fiorito",$C$5:$C$211,H29) -> 248800 | K29: =IF(SUMIF($A$5:$A$211,"Fiorito",$D$5:$D$211)=0,0,I29/SUMIF($A$5:$A$211,"Fiorito",$D$5:$D$211)) -> 0.1025641
A30: Fiorito | B30: HELADO X BOCHA | C30: GIGANTE 2 BOCHAS | D30: 9 | E30: 1.44 | F30: 31500 | H30: 1/2 KILO | I30: =SUMIFS($D$5:$D$211,$A$5:$A$211,"Fiorito",$C$5:$C$211,H30) -> 34 | J30: =SUMIFS($F$5:$F$211,$A$5:$A$211,"Fiorito",$C$5:$C$211,H30) -> 324200 | K30: =IF(SUMIF($A$5:$A$211,"Fiorito",$D$5:$D$211)=0,0,I30/SUMIF($A$5:$A$211,"Fiorito",$D$5:$D$211)) -> 0.087179487
A31: Fiorito | B31: HELADO X BOCHA | C31: GIGANTE 3 BOCHAS | D31: 7 | E31: 1.68 | F31: 27300 | H31: PALITO FRUTAL FRUTILLA X UNIDAD | I31: =SUMIFS($D$5:$D$211,$A$5:$A$211,"Fiorito",$C$5:$C$211,H31) -> 9 | J31: =SUMIFS($F$5:$F$211,$A$5:$A$211,"Fiorito",$C$5:$C$211,H31) -> 7200 | K31: =IF(SUMIF($A$5:$A$211,"Fiorito",$D$5:$D$211)=0,0,I31/SUMIF($A$5:$A$211,"Fiorito",$D$5:$D$211)) -> 0.023076923
A32: Fiorito | B32: HELADO X BOCHA | C32: CUCURUCHO GRIDO 3 BOCHAS | D32: 2 | E32: 0.48 | F32: 8200 | H32: CAPUCCINO GRIDO | I32: =SUMIFS($D$5:$D$211,$A$5:$A$211,"Fiorito",$C$5:$C$211,H32) -> 9 | J32: =SUMIFS($F$5:$F$211,$A$5:$A$211,"Fiorito",$C$5:$C$211,H32) -> 39600 | K32: =IF(SUMIF($A$5:$A$211,"Fiorito",$D$5:$D$211)=0,0,I32/SUMIF($A$5:$A$211,"Fiorito",$D$5:$D$211)) -> 0.023076923
A33: Fiorito | B33: HELADO X BOCHA | C33: MINI GIGANTE | D33: 1 | E33: 0.08 | F33: 2800 | H33: GIGANTE 2 BOCHAS | I33: =SUMIFS($D$5:$D$211,$A$5:$A$211,"Fiorito",$C$5:$C$211,H33) -> 9 | J33: =SUMIFS($F$5:$F$211,$A$5:$A$211,"Fiorito",$C$5:$C$211,H33) -> 31500 | K33: =IF(SUMIF($A$5:$A$211,"Fiorito",$D$5:$D$211)=0,0,I33/SUMIF($A$5:$A$211,"Fiorito",$D$5:$D$211)) -> 0.023076923
A34: Fiorito | B34: HELADO X BOCHA | C34: TACITA 2 BOCHAS | D34: 1 | E34: 0.16 | F34: 3500 | H34: PALITO BOMBÓN X10 UN. | I34: =SUMIFS($D$5:$D$211,$A$5:$A$211,"Fiorito",$C$5:$C$211,H34) -> 9 | J34: =SUMIFS($F$5:$F$211,$A$5:$A$211,"Fiorito",$C$5:$C$211,H34) -> 67900 | K34: =IF(SUMIF($A$5:$A$211,"Fiorito",$D$5:$D$211)=0,0,I34/SUMIF($A$5:$A$211,"Fiorito",$D$5:$D$211)) -> 0.023076923
A35: Fiorito | B35: HELADO X BOCHA | C35: TACITA 3 BOCHAS | D35: 1 | E35: 0.24 | F35: 3900 | H35: CUPS BLACK X 3 | I35: =SUMIFS($D$5:$D$211,$A$5:$A$211,"Fiorito",$C$5:$C$211,H35) -> 8 | J35: =SUMIFS($F$5:$F$211,$A$5:$A$211,"Fiorito",$C$5:$C$211,H35) -> 9600 | K35: =IF(SUMIF($A$5:$A$211,"Fiorito",$D$5:$D$211)=0,0,I35/SUMIF($A$5:$A$211,"Fiorito",$D$5:$D$211)) -> 0.020512821
A36: Fiorito | B36: HELADO X BOCHA | C36: GRIDOTOY 2 B. CUCU PUQUI MUCHI | D36: 1 | E36: 0.16 | F36: 5000 | H36: PALITO BOMBON DDL X UN. | I36: =SUMIFS($D$5:$D$211,$A$5:$A$211,"Fiorito",$C$5:$C$211,H36) -> 7 | J36: =SUMIFS($F$5:$F$211,$A$5:$A$211,"Fiorito",$C$5:$C$211,H36) -> 7370 | K36: =IF(SUMIF($A$5:$A$211,"Fiorito",$D$5:$D$211)=0,0,I36/SUMIF($A$5:$A$211,"Fiorito",$D$5:$D$211)) -> 0.017948718
A37: Fiorito | B37: HELADO X BOCHA | C37: BAÑO DE CHOCOLATE | D37: 1 | E37: 0 | F37: 700 | H37: FRAMBUESAS DOBLE CHOCOLATE - GRIDO | I37: =SUMIFS($D$5:$D$211,$A$5:$A$211,"Fiorito",$C$5:$C$211,H37) -> 7 | J37: =SUMIFS($F$5:$F$211,$A$5:$A$211,"Fiorito",$C$5:$C$211,H37) -> 39200 | K37: =IF(SUMIF($A$5:$A$211,"Fiorito",$D$5:$D$211)=0,0,I37/SUMIF($A$5:$A$211,"Fiorito",$D$5:$D$211)) -> 0.017948718
A38: Fiorito | B38: HELADO X BOCHA | C38: GRIDOTOY 1 B.TACITA PUQUI MUCHI | D38: 1 | E38: 0.08 | F38: 4400
A39: Fiorito | B39: HELADO X BOCHA | C39: GRIDOTOY 1 B. CUCU. PUQUI MUCHI | D39: 1 | E39: 0.08 | F39: 4400
A40: Fiorito | B40: LINEAS ESPECIALES | C40: HEL. "DUL. EQUI. FRUTI" 80 GR XU. | D40: 2 | E40: 0.16 | F40: 6200
A41: Fiorito | B41: LINEAS ESPECIALES | C41: HEL. "DUL. EQUI. CHOCO" 80 GR XU. | D41: 1 | E41: 0.08 | F41: 3100
A42: Fiorito | B42: PALITOS | C42: PALITO FRUTAL FRUTILLA X UNIDAD | D42: 9 | E42: 0.495 | F42: 7200
A43: Fiorito | B43: PALITOS | C43: PALITO BOMBÓN X10 UN. | D43: 9 | E43: 4.5 | F43: 67900
A44: Fiorito | B44: PALITOS | C44: PALITO BOMBON DDL X UN. | D44: 7 | E44: 0.35 | F44: 7370
A45: Fiorito | B45: PALITOS | C45: P.CREM.FRUTILLA X UNIDAD | D45: 6 | E45: 0.24 | F45: 5400
A46: Fiorito | B46: PALITOS | C46: PALITO BOMBÓN DDL X 10 | D46: 4 | E46: 2 | F46: 27010
A47: Fiorito | B47: PALITOS | C47: PALITO BOMBON X UNIDAD | D47: 4 | E47: 0.2 | F47: 4400
A48: Fiorito | B48: PALITOS | C48: PALITO CREMOSO AMERICANA X10 U. | D48: 3 | E48: 1.23 | F48: 17400 | H48: TOP 10 PRODUCTOS POR CANTIDAD · ESCALADA
A49: Fiorito | B49: PALITOS | C49: PALITO FRUTAL NARANJA X UNIDAD | D49: 3 | E49: 0.165 | F49: 2400 | H49: Producto | I49: Cantidad | J49: Venta | K49: % de las unidades
A50: Fiorito | B50: PALITOS | C50: PALITO FRUTAL NARANJA X10 U. | D50: 2 | E50: 1.1 | F50: 10600 | H50: 1 KILO | I50: =SUMIFS($D$5:$D$211,$A$5:$A$211,"Escalada",$C$5:$C$211,H50) -> 23 | J50: =SUMIFS($F$5:$F$211,$A$5:$A$211,"Escalada",$C$5:$C$211,H50) -> 419250 | K50: =IF(SUMIF($A$5:$A$211,"Escalada",$D$5:$D$211)=0,0,I50/SUMIF($A$5:$A$211,"Escalada",$D$5:$D$211)) -> 0.091269841
A51: Fiorito | B51: PALITOS | C51: P.FRUT.FRUTILLA EN CAJA X 20 | D51: 2 | E51: 2.2 | F51: 21000 | H51: 1/2 KILO | I51: =SUMIFS($D$5:$D$211,$A$5:$A$211,"Escalada",$C$5:$C$211,H51) -> 17 | J51: =SUMIFS($F$5:$F$211,$A$5:$A$211,"Escalada",$C$5:$C$211,H51) -> 166550 | K51: =IF(SUMIF($A$5:$A$211,"Escalada",$D$5:$D$211)=0,0,I51/SUMIF($A$5:$A$211,"Escalada",$D$5:$D$211)) -> 0.067460317
A52: Fiorito | B52: PALITOS | C52: PALITO FRUTAL LIMON X UNIDAD | D52: 2 | E52: 0.11 | F52: 1600 | H52: GIGANTE 2 BOCHAS | I52: =SUMIFS($D$5:$D$211,$A$5:$A$211,"Escalada",$C$5:$C$211,H52) -> 14 | J52: =SUMIFS($F$5:$F$211,$A$5:$A$211,"Escalada",$C$5:$C$211,H52) -> 42000 | K52: =IF(SUMIF($A$5:$A$211,"Escalada",$D$5:$D$211)=0,0,I52/SUMIF($A$5:$A$211,"Escalada",$D$5:$D$211)) -> 0.055555556
A53: Fiorito | B53: PALITOS | C53: PALITO CREMOSO FRUTILLA X10 U. | D53: 2 | E53: 0.82 | F53: 11600 | H53: 1/4 KILO | I53: =SUMIFS($D$5:$D$211,$A$5:$A$211,"Escalada",$C$5:$C$211,H53) -> 12 | J53: =SUMIFS($F$5:$F$211,$A$5:$A$211,"Escalada",$C$5:$C$211,H53) -> 78850 | K53: =IF(SUMIF($A$5:$A$211,"Escalada",$D$5:$D$211)=0,0,I53/SUMIF($A$5:$A$211,"Escalada",$D$5:$D$211)) -> 0.047619048
A54: Fiorito | B54: PALITOS | C54: P.CREM.AMERICANA X UNIDAD | D54: 1 | E54: 0.04 | F54: 900 | H54: FRAMBUESAS DOBLE CHOCOLATE - GRIDO | I54: =SUMIFS($D$5:$D$211,$A$5:$A$211,"Escalada",$C$5:$C$211,H54) -> 11 | J54: =SUMIFS($F$5:$F$211,$A$5:$A$211,"Escalada",$C$5:$C$211,H54) -> 64400 | K54: =IF(SUMIF($A$5:$A$211,"Escalada",$D$5:$D$211)=0,0,I54/SUMIF($A$5:$A$211,"Escalada",$D$5:$D$211)) -> 0.043650794
A55: Fiorito | B55: POSTRES | C55: BOMBON FRUTEZZA XU. | D55: 6 | E55: 0.444 | F55: 12000 | H55: BOMBON ESCOCES EN CAJA X 8 | I55: =SUMIFS($D$5:$D$211,$A$5:$A$211,"Escalada",$C$5:$C$211,H55) -> 10 | J55: =SUMIFS($F$5:$F$211,$A$5:$A$211,"Escalada",$C$5:$C$211,H55) -> 152000 | K55: =IF(SUMIF($A$5:$A$211,"Escalada",$D$5:$D$211)=0,0,I55/SUMIF($A$5:$A$211,"Escalada",$D$5:$D$211)) -> 0.03968254
A56: Fiorito | B56: POSTRES | C56: BOMBON ESCOCES X UNIDAD | D56: 5 | E56: 0.45 | F56: 12000 | H56: TORTA GRIDO RELLENA | I56: =SUMIFS($D$5:$D$211,$A$5:$A$211,"Escalada",$C$5:$C$211,H56) -> 9 | J56: =SUMIFS($F$5:$F$211,$A$5:$A$211,"Escalada",$C$5:$C$211,H56) -> 159500 | K56: =IF(SUMIF($A$5:$A$211,"Escalada",$D$5:$D$211)=0,0,I56/SUMIF($A$5:$A$211,"Escalada",$D$5:$D$211)) -> 0.035714286
A57: Fiorito | B57: POSTRES | C57: BOMBÓN CHOCO AVELLANAS X UN | D57: 5 | E57: 0.4 | F57: 12000 | H57: PALITO BOMBON X UNIDAD | I57: =SUMIFS($D$5:$D$211,$A$5:$A$211,"Escalada",$C$5:$C$211,H57) -> 9 | J57: =SUMIFS($F$5:$F$211,$A$5:$A$211,"Escalada",$C$5:$C$211,H57) -> 9900 | K57: =IF(SUMIF($A$5:$A$211,"Escalada",$D$5:$D$211)=0,0,I57/SUMIF($A$5:$A$211,"Escalada",$D$5:$D$211)) -> 0.035714286
A58: Fiorito | B58: POSTRES | C58: BOMBON ESCOCES EN CAJA X 8 | D58: 4 | E58: 2.88 | F58: 57200 | H58: BOMBON FRUTEZZA XU. | I58: =SUMIFS($D$5:$D$211,$A$5:$A$211,"Escalada",$C$5:$C$211,H58) -> 8 | J58: =SUMIFS($F$5:$F$211,$A$5:$A$211,"Escalada",$C$5:$C$211,H58) -> 16800 | K58: =IF(SUMIF($A$5:$A$211,"Escalada",$D$5:$D$211)=0,0,I58/SUMIF($A$5:$A$211,"Escalada",$D$5:$D$211)) -> 0.031746032
A59: Fiorito | B59: POSTRES | C59: CROCANTINO | D59: 4 | E59: 2.6 | F59: 44500 | H59: PALITO BOMBÓN X10 UN. | I59: =SUMIFS($D$5:$D$211,$A$5:$A$211,"Escalada",$C$5:$C$211,H59) -> 7 | J59: =SUMIFS($F$5:$F$211,$A$5:$A$211,"Escalada",$C$5:$C$211,H59) -> 54400 | K59: =IF(SUMIF($A$5:$A$211,"Escalada",$D$5:$D$211)=0,0,I59/SUMIF($A$5:$A$211,"Escalada",$D$5:$D$211)) -> 0.027777778
A60: Fiorito | B60: POSTRES | C60: BOMBON FRUTEZZA X8U. | D60: 3 | E60: 1.776 | F60: 39900
A61: Fiorito | B61: POSTRES | C61: BOMBÓN CHOCO AVELLANAS CAJA X 8 | D61: 3 | E61: 1.92 | F61: 42900
A62: Fiorito | B62: POSTRES | C62: ALMENDRADO EN CAJA X 8 | D62: 3 | E62: 2.04 | F62: 32100
A63: Fiorito | B63: POSTRES | C63: BOMBON SUIZO X UNIDAD | D63: 2 | E63: 0.17 | F63: 4600
A64: Fiorito | B64: POSTRES | C64: BOMBON CROCANTE EN CAJA X 8 | D64: 2 | E64: 1.12 | F64: 19950
A65: Fiorito | B65: POSTRES | C65: BOMBON SUIZO EN CAJA X 8 | D65: 1 | E65: 0.68 | F65: 13800
A66: Fiorito | B66: POSTRES | C66: CASATTA EN CAJA X 8 | D66: 1 | E66: 0.6 | F66: 10700
A67: Fiorito | B67: POSTRES | C67: BARRA DELICIA CHOCOLATE Y MANI | D67: 1 | E67: 0.6 | F67: 10700
A68: Fiorito | B68: SALSAS | C68: SALSA FRUTILLA X 500 | D68: 1 | E68: 0 | F68: 6000
A69: Fiorito | B69: TENTACION | C69: TODDY GALLETITAS | D69: 4 | E69: 2.76 | F69: 35200
A70: Fiorito | B70: TENTACION | C70: T. CHOC.ALMENDRAS | D70: 4 | E70: 2.76 | F70: 35200 | H70: TOP 10 PRODUCTOS POR CANTIDAD · LANUS OESTE
A71: Fiorito | B71: TENTACION | C71: T.1 LT DDL GRANIZADO | D71: 3 | E71: 2.07 | F71: 26400 | H71: Producto | I71: Cantidad | J71: Venta | K71: % de las unidades
A72: Fiorito | B72: TENTACION | C72: T. MENTA GRANIZADA | D72: 2 | E72: 1.38 | F72: 20100 | H72: 1 KILO | I72: =SUMIFS($D$5:$D$211,$A$5:$A$211,"Lanus Oeste",$C$5:$C$211,H72) -> 41 | J72: =SUMIFS($F$5:$F$211,$A$5:$A$211,"Lanus Oeste",$C$5:$C$211,H72) -> 655720 | K72: =IF(SUMIF($A$5:$A$211,"Lanus Oeste",$D$5:$D$211)=0,0,I72/SUMIF($A$5:$A$211,"Lanus Oeste",$D$5:$D$211)) -> 0.12654321
A73: Fiorito | B73: TENTACION | C73: T.1 LT FRUTILLA | D73: 2 | E73: 1.38 | F73: 17600 | H73: 1/4 KILO | I73: =SUMIFS($D$5:$D$211,$A$5:$A$211,"Lanus Oeste",$C$5:$C$211,H73) -> 33 | J73: =SUMIFS($F$5:$F$211,$A$5:$A$211,"Lanus Oeste",$C$5:$C$211,H73) -> 180400.03 | K73: =IF(SUMIF($A$5:$A$211,"Lanus Oeste",$D$5:$D$211)=0,0,I73/SUMIF($A$5:$A$211,"Lanus Oeste",$D$5:$D$211)) -> 0.10185185
A74: Fiorito | B74: TENTACION | C74: T. COOKIE | D74: 2 | E74: 1.38 | F74: 17600 | H74: 1/2 KILO | I74: =SUMIFS($D$5:$D$211,$A$5:$A$211,"Lanus Oeste",$C$5:$C$211,H74) -> 21 | J74: =SUMIFS($F$5:$F$211,$A$5:$A$211,"Lanus Oeste",$C$5:$C$211,H74) -> 167000 | K74: =IF(SUMIF($A$5:$A$211,"Lanus Oeste",$D$5:$D$211)=0,0,I74/SUMIF($A$5:$A$211,"Lanus Oeste",$D$5:$D$211)) -> 0.064814815
A75: Fiorito | B75: TENTACION | C75: T.CHOCOLATE | D75: 1 | E75: 0.69 | F75: 8800 | H75: FRAMBUESAS DOBLE CHOCOLATE - GRIDO | I75: =SUMIFS($D$5:$D$211,$A$5:$A$211,"Lanus Oeste",$C$5:$C$211,H75) -> 15 | J75: =SUMIFS($F$5:$F$211,$A$5:$A$211,"Lanus Oeste",$C$5:$C$211,H75) -> 84000 | K75: =IF(SUMIF($A$5:$A$211,"Lanus Oeste",$D$5:$D$211)=0,0,I75/SUMIF($A$5:$A$211,"Lanus Oeste",$D$5:$D$211)) -> 0.046296296
A76: Fiorito | B76: TENTACION | C76: T.DDLECHE | D76: 1 | E76: 0.69 | F76: 8800 | H76: PALITO BOMBÓN X10 UN. | I76: =SUMIFS($D$5:$D$211,$A$5:$A$211,"Lanus Oeste",$C$5:$C$211,H76) -> 13 | J76: =SUMIFS($F$5:$F$211,$A$5:$A$211,"Lanus Oeste",$C$5:$C$211,H76) -> 87600 | K76: =IF(SUMIF($A$5:$A$211,"Lanus Oeste",$D$5:$D$211)=0,0,I76/SUMIF($A$5:$A$211,"Lanus Oeste",$D$5:$D$211)) -> 0.040123457
A77: Fiorito | B77: TENTACION | C77: T. LIMON | D77: 1 | E77: 0.69 | F77: 8800 | H77: BOMBON ESCOCES X UNIDAD | I77: =SUMIFS($D$5:$D$211,$A$5:$A$211,"Lanus Oeste",$C$5:$C$211,H77) -> 12 | J77: =SUMIFS($F$5:$F$211,$A$5:$A$211,"Lanus Oeste",$C$5:$C$211,H77) -> 28800 | K77: =IF(SUMIF($A$5:$A$211,"Lanus Oeste",$D$5:$D$211)=0,0,I77/SUMIF($A$5:$A$211,"Lanus Oeste",$D$5:$D$211)) -> 0.037037037
A78: Fiorito | B78: TORTAS | C78: TORTA COOKIES AND CREAM | D78: 6 | E78: 6.27 | F78: 105000 | H78: GIGANTE 2 BOCHAS | I78: =SUMIFS($D$5:$D$211,$A$5:$A$211,"Lanus Oeste",$C$5:$C$211,H78) -> 10 | J78: =SUMIFS($F$5:$F$211,$A$5:$A$211,"Lanus Oeste",$C$5:$C$211,H78) -> 35000 | K78: =IF(SUMIF($A$5:$A$211,"Lanus Oeste",$D$5:$D$211)=0,0,I78/SUMIF($A$5:$A$211,"Lanus Oeste",$D$5:$D$211)) -> 0.030864198
A79: Fiorito | B79: TORTAS | C79: TORTA GRIDO RELLENA | D79: 5 | E79: 5.225 | F79: 84000 | H79: BOMBON FRUTEZZA X8U. | I79: =SUMIFS($D$5:$D$211,$A$5:$A$211,"Lanus Oeste",$C$5:$C$211,H79) -> 10 | J79: =SUMIFS($F$5:$F$211,$A$5:$A$211,"Lanus Oeste",$C$5:$C$211,H79) -> 127680 | K79: =IF(SUMIF($A$5:$A$211,"Lanus Oeste",$D$5:$D$211)=0,0,I79/SUMIF($A$5:$A$211,"Lanus Oeste",$D$5:$D$211)) -> 0.030864198
A80: Fiorito | B80: TORTAS | C80: TORTA FRUTILLAS CON CREMA | D80: 4 | E80: 4.18 | F80: 70000 | H80: BOMBON ESCOCES EN CAJA X 8 | I80: =SUMIFS($D$5:$D$211,$A$5:$A$211,"Lanus Oeste",$C$5:$C$211,H80) -> 9 | J80: =SUMIFS($F$5:$F$211,$A$5:$A$211,"Lanus Oeste",$C$5:$C$211,H80) -> 118690 | K80: =IF(SUMIF($A$5:$A$211,"Lanus Oeste",$D$5:$D$211)=0,0,I80/SUMIF($A$5:$A$211,"Lanus Oeste",$D$5:$D$211)) -> 0.027777778
A81: Escalada | B81: CAFETERIA | C81: CAFÉ CON LECHE GRANDE | D81: 5 | E81: 0 | F81: 16500 | H81: BOMBÓN CHOCO AVELLANAS X UN | I81: =SUMIFS($D$5:$D$211,$A$5:$A$211,"Lanus Oeste",$C$5:$C$211,H81) -> 9 | J81: =SUMIFS($F$5:$F$211,$A$5:$A$211,"Lanus Oeste",$C$5:$C$211,H81) -> 21600 | K81: =IF(SUMIF($A$5:$A$211,"Lanus Oeste",$D$5:$D$211)=0,0,I81/SUMIF($A$5:$A$211,"Lanus Oeste",$D$5:$D$211)) -> 0.027777778
A82: Escalada | B82: CAFETERIA | C82: TORTA COCO C/DULCE DE LECHE 120G. | D82: 3 | E82: 0.36 | F82: 9600
A83: Escalada | B83: CAFETERIA | C83: CAFE CAPUCCINO | D83: 2 | E83: 0 | F83: 6600
A84: Escalada | B84: CAFETERIA | C84: MATE COCIDO GRANDE | D84: 2 | E84: 0 | F84: 1200
A85: Escalada | B85: CAFETERIA | C85: CAFÉ ESPRESSO DOBLE GRANDE | D85: 1 | E85: 0 | F85: 3300
A86: Escalada | B86: CONGELADOS | C86: FRAMBUESAS DOBLE CHOCOLATE - GRIDO | D86: 11 | E86: 1.32 | F86: 64400
A87: Escalada | B87: CONGELADOS | C87: FRUTILLAS DOBLE CHOCOLATE - GRIDO | D87: 1 | E87: 0.12 | F87: 5600
A88: Escalada | B88: CUCURUCH. | C88: CUPS CLÁSICO BOCA ANCHA X3 | D88: 5 | E88: 0 | F88: 9600
A89: Escalada | B89: CUCURUCH. | C89: CUPS BLACK X 3 | D89: 1 | E89: 0 | F89: 1200
A90: Escalada | B90: DESCUENTOS | C90: DESCUENTO CUPONES | D90: 2 | E90: 0 | F90: -5999.98
A91: Escalada | B91: FAMILIAR | C91: FAMNº1 (CHOCOLATE/D.LECHE/AMERICANA) | D91: 1 | E91: 1.6 | F91: 17600
A92: Escalada | B92: FAMILIAR | C92: FAMNº4 (D.LECHE G/VAINILLA/CHOCOLATE) | D92: 1 | E92: 1.6 | F92: 23700
A93: Escalada | B93: FRIZZIO | C93: PECHUGUITA DE POLLO | D93: 1 | E93: 0.38 | F93: 6400
... A211: Lanus Oeste | B211: TORTAS | C211: TORTA GRIDO RELLENA | D211: 2 | E211: 2.09 | F211: 35000
A212: TOTAL | D212: =SUM(D5:D211) -> 966 | E212: =SUM(E5:E211) -> 411.828 | F212: =SUM(F5:F211) -> 7277663

Sheet Promociones
A1: PROMOCIONES · 27/09/2026
A2: Qué productos salieron dentro de cada promoción y cuántas veces se usó cada una. Fuente: DF_DTW.
A4: Sucursal | B4: Promoción | C4: Producto | D4: Cantidad | E4: Kilos | F4: Venta | G4: Descuento | I4: USOS POR PROMOCIÓN
A5: Fiorito | B5: 20% Jubilados Torta | C5: TORTA GRIDO RELLENA | D5: 1 | E5: 1.045 | F5: 14000 | G5: 3500 | I5: Promoción | J5: Fiorito | K5: Escalada | L5: Lanus Oeste | M5: Total
A6: Fiorito | B6: Promo-1kg+1/4 PEYA | C6: 1 KILO | D6: 2 | E6: 2 | F6: 27400 | G6: 0 | I6: 20% Jubilados Nuevo | J6: 0 | K6: 3 | L6: 12 | M6: =SUM(J6:L6) -> 15
A7: Fiorito | B7: Promo-1kg+1/4 PEYA | C7: 1/4 KILO | D7: 2 | E7: 0.5 | F7: 27400 | G7: 0 | I7: 20% Jubilados Torta | J7: 1 | K7: 2 | L7: 0 | M7: =SUM(J7:L7) -> 3
A8: Escalada | B8: 20% Jubilados Nuevo | C8: ALMENDRADO EN CAJA X 8 | D8: 1 | E8: 0.68 | F8: 8560 | G8: 2140 | I8: 3X2 en Cuarto - Pedi Grido | J8: 0 | K8: 0 | L8: 3 | M8: =SUM(J8:L8) -> 3
A9: Escalada | B9: 20% Jubilados Nuevo | C9: TORTA FRUTILLAS CON CREMA | D9: 1 | E9: 1.045 | F9: 14000 | G9: 3500 | I9: Promo-1kg+1/4 PEYA | J9: 2 | K9: 0 | L9: 0 | M9: =SUM(J9:L9) -> 2
A10: Escalada | B10: 20% Jubilados Nuevo | C10: TORTA COOKIES AND CREAM | D10: 1 | E10: 1.045 | F10: 14000 | G10: 3500 | I10: Promo-2*1/4kg PEYA | J10: 0 | K10: 1 | L10: 0 | M10: =SUM(J10:L10) -> 1
A11: Escalada | B11: 20% Jubilados Torta | C11: TORTA GRIDO RELLENA | D11: 2 | E11: 2.09 | F11: 28000 | G11: 7000 | I11: Promo 1/2+1/4 Apps | J11: 0 | K11: 1 | L11: 0 | M11: =SUM(J11:L11) -> 1
A12: Escalada | B12: Promo 1/2+1/4 Apps | C12: 1/2 KILO | D12: 1 | E12: 0.5 | F12: 9350 | G12: 0 | I12: 2 Kilos 25% OFF - Pedi Grido | J12: 0 | K12: 0 | L12: 1 | M12: =SUM(J12:L12) -> 1
A13: Escalada | B13: Promo 1/2+1/4 Apps | C13: 1/4 KILO | D13: 1 | E13: 0.25 | F13: 9350 | G13: 0 | I13: CAFE GRANDE 12 OZ T.NESPRESSO + MUFFIN | J13: 0 | K13: 0 | L13: 1 | M13: =SUM(J13:L13) -> 1
A14: Escalada | B14: Promo-2*1/4kg PEYA | C14: 1/4 KILO | D14: 2 | E14: 0.5 | F14: 15000 | G14: 0 | I14: TOTAL | J14: =SUM(J6:J13) -> 3 | K14: =SUM(K6:K13) -> 7 | L14: =SUM(L6:L13) -> 17 | M14: =SUM(M6:M13) -> 27
A15: Lanus Oeste | B15: 2 Kilos 25% OFF - Pedi Grido | C15: 1 KILO | D15: 2 | E15: 2 | F15: 25350 | G15: 0 | I15: Usos = veces que se aplicó la promoción. Las promos de apps (PedidosYa / Apps) no registran descuento en el POS.
A16: Lanus Oeste | B16: 20% Jubilados Nuevo | C16: 1 KILO | D16: 6 | E16: 6 | F16: 81120 | G16: 20280
A17: Lanus Oeste | B17: 20% Jubilados Nuevo | C17: BOMBON FRUTEZZA X8U. | D17: 2 | E17: 1.184 | F17: 21280 | G17: 5320
A18: Lanus Oeste | B18: 20% Jubilados Nuevo | C18: PALITO BOMBÓN X10 UN. | D18: 2 | E18: 1 | F18: 11680 | G18: 2920
A19: Lanus Oeste | B19: 20% Jubilados Nuevo | C19: ALMENDRADO EN CAJA X 8 | D19: 1 | E19: 0.68 | F19: 8560 | G19: 2140
A20: Lanus Oeste | B20: 20% Jubilados Nuevo | C20: BOMBON ESCOCES EN CAJA X 8 | D20: 1 | E20: 0.72 | F20: 11440 | G20: 2860
A21: Lanus Oeste | B21: 3X2 en Cuarto - Pedi Grido | C21: 1/4 KILO | D21: 9 | E21: 2.25 | F21: 38400.03 | G21: 0
A22: Lanus Oeste | B22: CAFE GRANDE 12 OZ T.NESPRESSO + MUFFIN | C22: MUFFIN VAINILLA | D22: 1 | E22: 0 | F22: 3250 | G22: 1550
A23: Lanus Oeste | B23: CAFE GRANDE 12 OZ T.NESPRESSO + MUFFIN | C23: CAFÉ CON LECHE GRANDE | D23: 1 | E23: 0 | F23: 3250 | G23: 50
A24: TOTAL | D24: =SUM(D5:D23) -> 39 | E24: =SUM(E5:E23) -> 23.489 | F24: =SUM(F5:F23) -> 371390.03 | G24: =SUM(G5:G23) -> 54760

Sheet Sobreventas
A1: SOBREVENTAS · 27/09/2026
A2: Qué productos se llevaron como sobreventa y cómo convirtió cada sucursal. Ofrecidas y aceptadas salen de la hoja «Informe Diario».
A4: Sucursal | B4: Sobreventa | C4: Producto | D4: Cantidad | E4: Kilos | F4: Venta | G4: Descuento | I4: OFRECIDAS Y ACEPTADAS · según Informe Diario
A5: Fiorito | B5: 2026 SV- 1/2 KILO | C5: 1/2 KILO | D5: 6 | E5: 3 | F5: 48000 | G5: 12000 | I5: Sucursal | J5: Ofrecidas | K5: Aceptadas | L5: Rechazadas | M5: % aceptación | N5: Estándar
A6: Fiorito | B6: 2026 SV 1/4 KILO | C6: 1/4 KILO | D6: 11 | E6: 2.75 | F6: 55000 | G6: 15400 | I6: ='Informe Diario'!A10 -> Fiorito | J6: ='Informe Diario'!J10 -> 162 | K6: ='Informe Diario'!K10 -> 23 | L6: =J6-K6 -> 139 | M6: =IF(J6=0,0,K6/J6) -> 0.14197531 | N6: 0.15
A7: Fiorito | B7: 2026 SV FRUTEZZA | C7: BOMBON FRUTEZZA XU. | D7: 6 | E7: 0.444 | F7: 12000 | G7: 1200 | I7: ='Informe Diario'!A15 -> Escalada | J7: ='Informe Diario'!J15 -> 85 | K7: ='Informe Diario'!K15 -> 14 | L7: =J7-K7 -> 71 | M7: =IF(J7=0,0,K7/J7) -> 0.16470588 | N7: 0.15
A8: Escalada | B8: 2026 SV- 1/2 KILO | C8: 1/2 KILO | D8: 5 | E8: 2.5 | F8: 40000 | G8: 10000 | I8: ='Informe Diario'!A21 -> Lanus Oeste | J8: ='Informe Diario'!J21 -> 146 | K8: ='Informe Diario'!K21 -> 13 | L8: =J8-K8 -> 133 | M8: =IF(J8=0,0,K8/J8) -> 0.089041096 | N8: 0.15
A9: Escalada | B9: 2026 SV 1/4 KILO | C9: 1/4 KILO | D9: 3 | E9: 0.75 | F9: 15000 | G9: 4200 | I9: TOTAL | J9: =SUM(J6:J8) -> 393 | K9: =SUM(K6:K8) -> 50 | L9: =SUM(L6:L8) -> 343 | M9: =IF(J9=0,0,K9/J9) -> 0.12722646 | N9: 0.15
A10: Escalada | B10: 2026 SV FRUTEZZA | C10: BOMBON FRUTEZZA XU. | D10: 4 | E10: 0.296 | F10: 8000 | G10: 800
A11: Escalada | B11: 2026 SV TORTA COCO | C11: TORTA COCO C/DULCE DE LECHE 120G. | D11: 3 | E11: 0.36 | F11: 9600 | G11: 4800
A12: Lanus Oeste | B12: 2026 SV- 1/2 KILO | C12: 1/2 KILO | D12: 4 | E12: 2 | F12: 32000 | G12: 8000 | I12: ACEPTADAS POR PRODUCTO
A13: Lanus Oeste | B13: 2026 SV 1/4 KILO | C13: 1/4 KILO | D13: 6 | E13: 1.5 | F13: 30000 | G13: 8400 | I13: Producto | J13: Cantidad | K13: Venta | L13: % de las unidades
A14: Lanus Oeste | B14: 2026 SV FRUTEZZA | C14: BOMBON FRUTEZZA XU. | D14: 2 | E14: 0.148 | F14: 4000 | G14: 400 | I14: 1/4 KILO | J14: =SUMIF($C$5:$C$15,I14,$D$5:$D$15) -> 20 | K14: =SUMIF($C$5:$C$15,I14,$F$5:$F$15) -> 100000 | L14: =IF($D$16=0,0,J14/$D$16) -> 0.39215686
A15: Lanus Oeste | B15: 2026 SV TORTA COCO | C15: TORTA COCO C/DULCE DE LECHE 120G. | D15: 1 | E15: 0.12 | F15: 3200 | G15: 1600 | I15: 1/2 KILO | J15: =SUMIF($C$5:$C$15,I15,$D$5:$D$15) -> 15 | K15: =SUMIF($C$5:$C$15,I15,$F$5:$F$15) -> 120000 | L15: =IF($D$16=0,0,J15/$D$16) -> 0.29411765
A16: TOTAL | D16: =SUM(D5:D15) -> 51 | E16: =SUM(E5:E15) -> 13.868 | F16: =SUM(F5:F15) -> 256800 | G16: =SUM(G5:G15) -> 66800 | I16: BOMBON FRUTEZZA XU. | J16: =SUMIF($C$5:$C$15,I16,$D$5:$D$15) -> 12 | K16: =SUMIF($C$5:$C$15,I16,$F$5:$F$15) -> 24000 | L16: =IF($D$16=0,0,J16/$D$16) -> 0.23529412
I17: TORTA COCO C/DULCE DE LECHE 120G. | J17: =SUMIF($C$5:$C$15,I17,$D$5:$D$15) -> 4 | K17: =SUMIF($C$5:$C$15,I17,$F$5:$F$15) -> 12800 | L17: =IF($D$16=0,0,J17/$D$16) -> 0.078431373
I19: Un ticket puede llevar más de una sobreventa: por eso la suma por producto puede superar las aceptadas del Informe Diario.

Sheet Tickets
A1: TICKETS DEL DÍA · DOMINGO 27/09/2026
A2: Un renglón por ticket: qué se llevó el cliente y qué pasó con la sobreventa. Usá los filtros (por ejemplo «Cajero») para ver a una persona.
A4: Sucursal | B4: Cajero | C4: Hora | D4: Canal | E4: Importe | F4: Rubro principal | G4: Producto llevado | H4: Sobreventa | I4: Producto llevado en SV
A5: Fiorito | B5: Ailen | C5: 17 h | D5: Salón | E5: 18400 | F5: FAMILIAR | G5: 1 FAMNº1 (CHOCOLATE/D.LECHE/AMERICANA) + 1 PALITO FRUTAL FRUTILLA X UNIDAD | H5: Rechazada
A6: Fiorito | B6: Ailen | C6: 17 h | D6: Salón | E6: 4400 | F6: GRIDOS | G6: 1 CAPUCCINO GRIDO | H6: Rechazada
A7: Fiorito | B7: Ailen | C7: 17 h | D7: Salón | E7: 19300 | F7: HELADO X KILO | G7: 1 1 KILO + 2 CUPS BLACK X 3 | H7: Rechazada
A8: Fiorito | B8: Ailen | C8: 17 h | D8: Salón | E8: 7300 | F8: PALITOS | G8: 1 PALITO BOMBÓN X10 UN. | H8: Rechazada
A9: Fiorito | B9: Ailen | C9: 17 h | D9: Salón | E9: 6400 | F9: HELADO X KILO | G9: 1 1/4 KILO | H9: Rechazada
A10: Fiorito | B10: Ailen | C10: 17 h | D10: Salón | E10: 3900 | F10: HELADO X BOCHA | G10: 1 TACITA 3 BOCHAS | H10: Rechazada
A11: Fiorito | B11: Ailen | C11: 17 h | D11: Salón | E11: 15000 | F11: HELADO X KILO | G11: 1 1/2 KILO | H11: Aceptada | I11: 1 1/4 KILO
A12: Fiorito | B12: Ailen | C12: 18 h | D12: Salón | E12: 19900 | F12: TORTAS | G12: 1 TORTA FRUTILLAS CON CREMA + 2 VELA NUMERO X UN | H12: Rechazada
A13: Fiorito | B13: Ailen | C13: 18 h | D13: Salón | E13: 4300 | F13: GRIDOS | G13: 1 GRIDO BATIDO | H13: Rechazada
A14: Fiorito | B14: Ailen | C14: 18 h | D14: Salón | E14: 18700 | F14: PALITOS | G14: 1 PALITO BOMBÓN DDL X 10 + 1 1/4 KILO | H14: Aceptada | I14: 1 1/4 KILO
A15: Fiorito | B15: Ailen | C15: 18 h | D15: Salón | E15: 16900 | F15: HELADO X KILO | G15: 1 1 KILO | H15: Rechazada
A16: Fiorito | B16: Ailen | C16: 18 h | D16: Salón | E16: 5600 | F16: CONGELADOS | G16: 1 FRAMBUESAS DOBLE CHOCOLATE - GRIDO | H16: Rechazada
A17: Fiorito | B17: Ailen | C17: 18 h | D17: Salón | E17: 1800 | F17: PALITOS | G17: 2 P.CREM.FRUTILLA X UNIDAD | H17: No ofrecida
A18: Fiorito | B18: Ailen | C18: 18 h | D18: Salón | E18: 19900 | F18: TORTAS | G18: 1 TORTA GRIDO RELLENA + 2 VELA NUMERO X UN | H18: Rechazada
A19: Fiorito | B19: Ailen | C19: 18 h | D19: Salón | E19: 17600 | F19: FAMILIAR | G19: 1 FAMNº1 (CHOCOLATE/D.LECHE/AMERICANA) | H19: Rechazada
A20: Fiorito | B20: Ailen | C20: 18 h | D20: Salón | E20: 17500 | F20: TORTAS | G20: 1 TORTA COOKIES AND CREAM | H20: Rechazada
A21: Fiorito | B21: Ailen | C21: 18 h | D21: Salón | E21: 13200 | F21: GRIDOS | G21: 3 CAPUCCINO GRIDO | H21: Rechazada
A22: Fiorito | B22: Ailen | C22: 18 h | D22: Salón | E22: 14000 | F22: TORTAS | G22: 1 TORTA GRIDO RELLENA | H22: Rechazada
A23: Fiorito | B23: Ailen | C23: 19 h | D23: Salón | E23: 7800 | F23: HELADO X BOCHA | G23: 2 GIGANTE 3 BOCHAS | H23: Rechazada
A24: Fiorito | B24: Ailen | C24: 19 h | D24: Salón | E24: 8800 | F24: TENTACION | G24: 1 T. CHOC.ALMENDRAS | H24: Rechazada
A25: Fiorito | B25: Ailen | C25: 19 h | D25: Salón | E25: 1100 | F25: PALITOS | G25: 1 PALITO BOMBON DDL X UN. | H25: No ofrecida
A26: Fiorito | B26: Ailen | C26: 19 h | D26: Salón | E26: 4400 | F26: GRIDOS | G26: 1 CAPUCCINO GRIDO | H26: Rechazada
... A31: Fiorito | B31: Ailen | C31: 19 h | D31: Salón | E31: 17600 | F31: FAMILIAR | G31: 1 FAMNº4 (D.LECHE G/VAINILLA/CHOCOLATE) | H31: Rechazada
A32: Fiorito | B32: Ailen | C32: 19 h | D32: Salón | E32: 22500 | F32: TORTAS | G32: 1 TORTA FRUTILLAS CON CREMA | H32: Aceptada | I32: 1 1/4 KILO
A33: Fiorito | B33: Ailen | C33: 19 h | D33: Salón | E33: 16900 | F33: HELADO X KILO | G33: 1 1 KILO | H33: Rechazada
A34: Fiorito | B34: Ailen | C34: 19 h | D34: Salón | E34: 16900 | F34: HELADO X KILO | G34: 1 1 KILO | H34: Rechazada
A35: Fiorito | B35: Ailen | C35: 19 h | D35: Salón | E35: 6000 | F35: SALSAS | G35: 1 SALSA FRUTILLA X 500 | H35: Rechazada
A36: Fiorito | B36: Ailen | C36: 20 h | D36: Salón | E36: 18600 | F36: TORTAS | G36: 1 TORTA FRUTILLAS CON CREMA + 1 PALITO BOMBON X UNIDAD | H36: Rechazada
A37: Fiorito | B37: Ailen | C37: 20 h | D37: Salón | E37: 10600 | F37: GRIDOS | G37: 1 GRIDO BATIDO + 1 TACITA 2 BOCHAS + 1 MINI GIGANTE | H37: Rechazada
A38: Fiorito | B38: Ailen | C38: 20 h | D38: Salón | E38: 16900 | F38: HELADO X KILO | G38: 1 1 KILO | H38: Rechazada
A39: Fiorito | B39: Ailen | C39: 20 h | D39: Salón | E39: 8500 | F39: HELADO X BOCHA | G39: 2 GIGANTE 3 BOCHAS + 1 BAÑO DE CHOCOLATE | H39: Rechazada
A40: Fiorito | B40: Ailen | C40: 20 h | D40: Salón | E40: 1800 | F40: PALITOS | G40: 2 P.CREM.FRUTILLA X UNIDAD | H40: No ofrecida
A41: Fiorito | B41: Ailen | C41: 20 h | D41: Salón | E41: 17300 | F41: HELADO X BOCHA | G41: 1 GRIDOTOY 2 B. CUCU PUQUI MUCHI + 1 CAPUCCINO GRIDO + 1 GRIDOTOY 1 B. CUCU. PUQUI MUCHI + 1 GIGANTE 2 BOCHAS | H41: Rechazada
A42: Fiorito | B42: Ailen | C42: 20 h | D42: Salón | E42: 26400 | F42: FAMILIAR | G42: 1 FAMNº4 (D.LECHE G/VAINILLA/CHOCOLATE) + 1 T. COOKIE | H42: Rechazada
A43: Fiorito | B43: Ailen | C43: 20 h | D43: Salón | E43: 16900 | F43: HELADO X KILO | G43: 1 1 KILO | H43: Rechazada
A44: Fiorito | B44: Ailen | C44: 20 h | D44: Salón | E44: 18000 | F44: HELADO X KILO | G44: 1 1/2 KILO | H44: Aceptada | I44: 1 1/2 KILO
A45: Fiorito | B45: Ailen | C45: 20 h | D45: Salón | E45: 25600 | F45: HELADO X KILO | G45: 4 1/4 KILO | H45: Rechazada
A46: Fiorito | B46: Ailen | C46: 20 h | D46: Salón | E46: 13300 | F46: POSTRES | G46: 1 BOMBON CROCANTE EN CAJA X 8 | H46: Rechazada
A47: Fiorito | B47: Ailen | C47: 20 h | D47: Salón | E47: 10000 | F47: HELADO X KILO | G47: 1 1/2 KILO | H47: Rechazada
A48: Fiorito | B48: Ailen | C48: 20 h | D48: Salón | E48: 10800 | F48: HELADO X KILO | G48: 1 1/4 KILO + 1 CAPUCCINO GRIDO | H48: Rechazada
A49: Fiorito | B49: Ailen | C49: 20 h | D49: Salón | E49: 29900 | F49: POSTRES | G49: 1 BOMBÓN CHOCO AVELLANAS CAJA X 8 + 2 FRUTILLAS DOBLE CHOCOLATE - GRIDO + 1 CAPUCCINO GRIDO | H49: Rechazada
A50: Fiorito | B50: Ailen | C50: 20 h | D50: Salón | E50: 12300 | F50: PALITOS | G50: 1 PALITO BOMBÓN X10 UN. | H50: Aceptada | I50: 1 1/4 KILO
A51: Fiorito | B51: Ailen | C51: 20 h | D51: Salón | E51: 4400 | F51: HELADO X BOCHA | G51: 1 GRIDOTOY 1 B.TACITA PUQUI MUCHI | H51: Rechazada
A52: Fiorito | B52: Ailen | C52: 20 h | D52: Salón | E52: 17500 | F52: TORTAS | G52: 1 TORTA COOKIES AND CREAM | H52: Rechazada
A53: Fiorito | B53: Ailen | C53: 20 h | D53: Salón | E53: 16900 | F53: HELADO X KILO | G53: 1 1 KILO | H53: Rechazada
A54: Fiorito | B54: Ailen | C54: 20 h | D54: Salón | E54: 6400 | F54: HELADO X KILO | G54: 1 1/4 KILO | H54: Rechazada
A55: Fiorito | B55: Ailen | C55: 21 h | D55: Salón | E55: 6400 | F55: HELADO X KILO | G55: 1 1/4 KILO | H55: Rechazada
A56: Fiorito | B56: Ailen | C56: 21 h | D56: Salón | E56: 10000 | F56: HELADO X KILO | G56: 1 1/2 KILO | H56: Rechazada
A57: Fiorito | B57: Ailen | C57: 21 h | D57: Salón | E57: 37400 | F57: TORTAS | G57: 1 TORTA COOKIES AND CREAM + 1 TORTA GRIDO RELLENA + 2 VELA NUMERO X UN | H57: Rechazada
A58: Fiorito | B58: Ailen | C58: 21 h | D58: Salón | E58: 10000 | F58: HELADO X KILO | G58: 1 1/2 KILO | H58: Rechazada
A59: Fiorito | B59: Ailen | C59: 21 h | D59: Salón | E59: 16900 | F59: HELADO X KILO | G59: 1 1 KILO | H59: Rechazada
A60: Fiorito | B60: Ailen | C60: 21 h | D60: Salón | E60: 16900 | F60: HELADO X KILO | G60: 1 1 KILO | H60: Rechazada
A61: Fiorito | B61: Ailen | C61: 21 h | D61: Salón | E61: 26300 | F61: HELADO X KILO | G61: 1 1 KILO + 4 PALITO BOMBON DDL X UN. | H61: Aceptada | I61: 1 1/4 KILO
A62: Fiorito | B62: Ailen | C62: 21 h | D62: Salón | E62: 11200 | F62: HELADO X KILO | G62: 1 1/2 KILO + 1 CUPS BLACK X 3 | H62: Rechazada
A63: Fiorito | B63: Ailen | C63: 21 h | D63: Salón | E63: 3000 | F63: PALITOS | G63: 1 PALITO BOMBON X UNIDAD + 1 PALITO BOMBON DDL X UN. + 1 PALITO FRUTAL NARANJA X UNIDAD | H63: Rechazada
A64: Fiorito | B64: Ailen | C64: 21 h | D64: Salón | E64: 10500 | F64: PALITOS | G64: 1 P.FRUT.FRUTILLA EN CAJA X 20 | H64: Rechazada
A65: Fiorito | B65: Ailen | C65: 21 h | D65: Salón | E65: 14300 | F65: POSTRES | G65: 1 BOMBON ESCOCES EN CAJA X 8 | H65: Rechazada
A66: Fiorito | B66: Ailen | C66: 21 h | D66: Salón | E66: 12800 | F66: HELADO X BOCHA | G66: 2 GIGANTE 2 BOCHAS + 1 PALITO CREMOSO FRUTILLA X10 U. | H66: Rechazada
A67: Fiorito | B67: Ailen | C67: 21 h | D67: Salón | E67: 12800 | F67: HELADO X KILO | G67: 2 1/4 KILO | H67: Rechazada
A68: Fiorito | B68: Ailen | C68: 21 h | D68: Salón | E68: 10600 | F68: PALITOS | G68: 2 PALITO FRUTAL NARANJA X10 U. | H68: Rechazada
A69: Fiorito | B69: Ailen | C69: 21 h | D69: Salón | E69: 14600 | F69: PALITOS | G69: 1 PALITO BOMBÓN DDL X 10 + 1 PALITO BOMBÓN X10 UN. | H69: Rechazada
A70: Fiorito | B70: Ailen | C70: 22 h | D70: Salón | E70: 10000 | F70: HELADO X KILO | G70: 1 1/2 KILO | H70: Rechazada
A71: Fiorito | B71: Ailen | C71: 22 h | D71: Salón | E71: 21200 | F71: CONGELADOS | G71: 2 FRAMBUESAS DOBLE CHOCOLATE - GRIDO + 1 1/2 KILO | H71: Rechazada
A72: Fiorito | B72: Ailen | C72: 22 h | D72: Salón | E72: 3500 | F72: HELADO X BOCHA | G72: 1 GIGANTE 2 BOCHAS | H72: Rechazada
A73: Fiorito | B73: Ailen | C73: 22 h | D73: Salón | E73: 10000 | F73: HELADO X KILO | G73: 1 1/2 KILO | H73: Rechazada
... A83: Fiorito | B83: Candela | C83: 10 h | D83: Salón | E83: 3300 | F83: CAFETERIA | G83: 1 CAFÉ ESPRESSO DOBLE GRANDE | H83: Rechazada
A84: Fiorito | B84: Candela | C84: 10 h | D84: Salón | E84: 6400 | F84: GRIDOS | G84: 1 CAPUCCINO GRIDO | H84: Aceptada | I84: 1 BOMBON FRUTEZZA XU.
A85: Fiorito | B85: Candela | C85: 10 h | D85: Salón | E85: 3500 | F85: HELADO X BOCHA | G85: 1 GIGANTE 2 BOCHAS | H85: Rechazada
A86: Fiorito | B86: Candela | C86: 11 h | D86: Salón | E86: 2200 | F86: CAFETERIA | G86: 1 CHOCOLATADA GRANDE + 1 MEDIALUNA EXTRA DULCE PRECOCIDA | H86: No ofrecida
A87: Fiorito | B87: Candela | C87: 11 h | D87: Salón | E87: 4700 | F87: LINEAS ESPECIALES | G87: 1 HEL. "DUL. EQUI. CHOCO" 80 GR XU. + 1 PALITO FRUTAL NARANJA X UNIDAD + 1 PALITO FRUTAL FRUTILLA X UNIDAD | H87: Rechazada
A88: Fiorito | B88: Candela | C88: 11 h | D88: Salón | E88: 8600 | F88: GRIDOS | G88: 2 GRIDO BATIDO | H88: Rechazada
A89: Fiorito | B89: Candela | C89: 11 h | D89: Salón | E89: 21900 | F89: HELADO X KILO | G89: 1 1 KILO | H89: Aceptada | I89: 1 1/4 KILO
A90: Fiorito | B90: Candela | C90: 11 h | D90: Salón | E90: 1200 | F90: CUCURUCH. | G90: 1 CUPS BLACK X 3 | H90: No ofrecida
A91: Fiorito | B91: Candela | C91: 11 h | D91: Salón | E91: 26400 | F91: POSTRES | G91: 1 ALMENDRADO EN CAJA X 8 + 1 CASATTA EN CAJA X 8 | H91: Aceptada | I91: 1 1/4 KILO
A92: Fiorito | B92: Candela | C92: 12 h | D92: Salón | E92: 17600 | F92: FAMILIAR | G92: 1 FAMNº3 (VAINILLA/FRUTILLA/GRANIZADO) | H92: Rechazada
A93: Fiorito | B93: Candela | C93: 12 h | D93: Salón | E93: 31000 | F93: POSTRES | G93: 2 BOMBON ESCOCES EN CAJA X 8 + 1 BOMBÓN CHOCO AVELLANAS X UN | H93: Rechazada
A94: Fiorito | B94: Candela | C94: 12 h | D94: Salón | E94: 35000 | F94: TORTAS | G94: 1 TORTA COOKIES AND CREAM + 1 TORTA GRIDO RELLENA | H94: Rechazada
A95: Fiorito | B95: Candela | C95: 13 h | D95: Salón | E95: 10000 | F95: HELADO X KILO | G95: 1 1/2 KILO | H95: Rechazada
A96: Fiorito | B96: Candela | C96: 13 h | D96: Salón | E96: 14600 | F96: PALITOS | G96: 2 PALITO BOMBÓN X10 UN. | H96: Rechazada
A97: Fiorito | B97: Candela | C97: 13 h | D97: Salón | E97: 16900 | F97: HELADO X KILO | G97: 1 1 KILO | H97: Rechazada
A98: Fiorito | B98: Candela | C98: 13 h | D98: Salón | E98: 33800 | F98: FAMILIAR | G98: 1 FAMNº4 (D.LECHE G/VAINILLA/CHOCOLATE) + 2 BOMBÓN CHOCO AVELLANAS X UN + 5 PALITO FRUTAL FRUTILLA X UNIDAD + 2 CUPS BLACK X 3 | H98: Aceptada | I98: 1 1/4 KILO
A99: Fiorito | B99: Candela | C99: 13 h | D99: Salón | E99: 36000 | F99: HELADO X KILO | G99: 2 1 KILO + 1 CUPS CLÁSICO BOCA ANCHA X3 + 1 CUPS CONITO X 5 UN. | H99: Rechazada
A100: Fiorito | B100: Candela | C100: 13 h | D100: Salón | E100: 8800 | F100: TENTACION | G100: 1 T.CHOCOLATE | H100: Rechazada
A101: Fiorito | B101: Candela | C101: 13 h | D101: Salón | E101: 6400 | F101: HELADO X KILO | G101: 1 1/4 KILO | H101: Rechazada
A102: Fiorito | B102: Candela | C102: 13 h | D102: Salón | E102: 27600 | F102: POSTRES | G102: 1 BOMBÓN CHOCO AVELLANAS CAJA X 8 + 1 BOMBON FRUTEZZA X8U. | H102: Rechazada
A103: Fiorito | B103: Candela | C103: 13 h | D103: Salón | E103: 7000 | F103: HELADO X BOCHA | G103: 2 GIGANTE 2 BOCHAS | H103: Rechazada
A104: Fiorito | B104: Candela | C104: 13 h | D104: Salón | E104: 2500 | F104: PALITOS | G104: 1 P.CREM.FRUTILLA X UNIDAD + 1 PALITO FRUTAL FRUTILLA X UNIDAD + 1 PALITO FRUTAL LIMON X UNIDAD | H104: Rechazada
A105: Fiorito | B105: Candela | C105: 13 h | D105: Salón | E105: 6400 | F105: HELADO X KILO | G105: 1 1/4 KILO | H105: Rechazada
A106: Fiorito | B106: Candela | C106: 14 h | D106: Salón | E106: 3900 | F106: HELADO X BOCHA | G106: 1 GIGANTE 3 BOCHAS | H106: Rechazada
A107: Fiorito | B107: Candela | C107: 14 h | D107: Salón | E107: 16900 | F107: HELADO X KILO | G107: 1 1 KILO | H107: Rechazada
A108: Fiorito | B108: Candela | C108: 14 h | D108: Salón | E108: 10000 | F108: HELADO X KILO | G108: 1 1/2 KILO | H108: Rechazada
A109: Fiorito | B109: Candela | C109: 14 h | D109: Salón | E109: 9600 | F109: TENTACION | G109: 1 T.1 LT FRUTILLA + 1 PALITO FRUTAL NARANJA X UNIDAD | H109: Rechazada
A110: Fiorito | B110: Candela | C110: 14 h | D110: Salón | E110: 41500 | F110: HELADO X KILO | G110: 1 1 KILO + 1 T. MENTA GRANIZADA + 1 PALITO CREMOSO AMERICANA X10 U. + 1 FRAMBUESAS DOBLE CHOCOLATE - GRIDO + 1 BOMBÓN CHOCO AVELLANAS X UN | H110: Aceptada | I110: 1 BOMBON FRUTEZZA XU.
A111: Fiorito | B111: Candela | C111: 14 h | D111: Salón | E111: 27600 | F111: POSTRES | G111: 1 BOMBÓN CHOCO AVELLANAS CAJA X 8 + 1 BOMBON FRUTEZZA X8U. | H111: Rechazada
A112: Fiorito | B112: Candela | C112: 14 h | D112: Salón | E112: 7300 | F112: PALITOS | G112: 1 PALITO BOMBÓN X10 UN. | H112: Rechazada
A113: Fiorito | B113: Candela | C113: 15 h | D113: Salón | E113: 9500 | F113: CONGELADOS | G113: 1 FRAMBUESAS DOBLE CHOCOLATE - GRIDO + 1 GIGANTE 3 BOCHAS | H113: Rechazada
A114: Fiorito | B114: Candela | C114: 15 h | D114: Salón | E114: 16900 | F114: HELADO X KILO | G114: 1 1 KILO | H114: Rechazada
...

Sheet Efemérides
A1: EFEMÉRIDES · DOMINGO 27/09/2026
A2: Fechas especiales del día y del año: feriados, días no laborables, calendario escolar y otras fechas que pueden mover la venta. Se editan en reportes\calendario\feriados.csv y efemerides.csv.
A4: PRÓXIMAMENTE
A7: En esta solapa se van a sumar las efemérides de cada día (fechas patrias, días especiales, eventos de la zona). Las que ya están cargadas también las usa el modelo de venta esperada.
A9: EL DÍA
A10: Fecha | B10: 46292
A11: Día | B11: Domingo
A12: ¿Feriado? | B12: No | C12: Día común, sin feriado ni día no laborable
A13: Efeméride | B13: No | C13: Sin efeméride comercial cargada
A14: Próximo feriado | B14: 46307 | C14: Lunes: Día del Respeto a la Diversidad Cultural
A15: Faltan (días) | B15: =B14-B10 -> 15
A17: CALENDARIO 2026 (Y HASTA EL 01/05/2027): FERIADOS, DÍAS NO LABORABLES Y FECHAS QUE PUEDEN AFECTAR LAS VENTAS
A18: Fecha | B18: Día | C18: Qué se celebra / qué pasa | D18: Tipo | E18: Faltan (días) | F18: Verificado
A19: 46023 | B19: Jueves | C19: Año Nuevo | D19: Feriado | E19: =A19-$B$10 -> -269 | F19: A verificar
A20: 46067 | B20: Sábado | C20: San Valentín | D20: Efeméride · Comercial | E20: =A20-$B$10 -> -225 | F20: Sí (fecha fija)
A21: 46069 | B21: Lunes | C21: Carnaval | D21: Feriado | E21: =A21-$B$10 -> -223 | F21: A verificar
A22: 46070 | B22: Martes | C22: Carnaval | D22: Feriado | E22: =A22-$B$10 -> -222 | F22: A verificar
A23: 46083 | B23: Lunes | C23: Inicio de clases (Prov. de Buenos Aires: Lanús y Lomas de Zamora) | D23: Efeméride · Escolar | E23: =A23-$B$10 -> -209 | F23: A verificar
A24: 46104 | B24: Lunes | C24: Día no laborable con fines turísticos | D24: Puente | E24: =A24-$B$10 -> -188 | F24: A verificar
A25: 46105 | B25: Martes | C25: Día de la Memoria | D25: Feriado | E25: =A25-$B$10 -> -187 | F25: A verificar
A26: 46114 | B26: Jueves | C26: Malvinas / Jueves Santo | D26: Feriado | E26: =A26-$B$10 -> -178 | F26: A verificar
A27: 46115 | B27: Viernes | C27: Viernes Santo | D27: Feriado | E27: =A27-$B$10 -> -177 | F27: A verificar
A28: 46117 | B28: Domingo | C28: Pascua (Domingo de Resurrección) | D28: Efeméride · Familiar | E28: =A28-$B$10 -> -175 | F28: Sí (calculada)
A29: 46143 | B29: Viernes | C29: Día del Trabajador | D29: Feriado | E29: =A29-$B$10 -> -149 | F29: A verificar
A30: 46167 | B30: Lunes | C30: Revolución de Mayo | D30: Feriado | E30: =A30-$B$10 -> -125 | F30: A verificar
... A74: 46508 | B74: Sábado | C74: Día del Trabajador | D74: Feriado | E74: =A74-$B$10 -> 216 | F74: Sí (calendario 2027 publicado)
A76: Feriados nacionales (los trasladables, en el día en que se gozan), días no laborables y puentes; y fechas que pueden mover la venta: calendario escolar de la Provincia de Buenos Aires (Lanús y Lomas de Zamora), fechas familiares y comerciales, cobro de aguinaldo, partidos y elecciones. «A verificar» = cargado de memoria o aproximado: confirmar con el calendario oficial (DGCyE para lo escolar). Se editan en reportes\calendario\feriados.csv y efemerides.csv. Incluye los feriados provinciales de la Provincia de Buenos Aires que se cargaron (ej. visita del Papa); no incluye feriados municipales.
